ntnx_opsmgmt_py_client/__init__.py
ntnx_opsmgmt_py_client/api_client.py
ntnx_opsmgmt_py_client/api_response.py
ntnx_opsmgmt_py_client/configuration.py
ntnx_opsmgmt_py_client/custom_retry.py
ntnx_opsmgmt_py_client/rest.py
ntnx_opsmgmt_py_client/api/__init__.py
ntnx_opsmgmt_py_client/api/global_report_setting_api.py
ntnx_opsmgmt_py_client/api/report_artifacts_api.py
ntnx_opsmgmt_py_client/api/report_config_api.py
ntnx_opsmgmt_py_client/api/reports_api.py
ntnx_opsmgmt_py_client/models/__init__.py
ntnx_opsmgmt_py_client/models/OneOfcommon/__init__.py
ntnx_opsmgmt_py_client/models/OneOfcommon/v1/__init__.py
ntnx_opsmgmt_py_client/models/OneOfcommon/v1/config/KVPairvalue.py
ntnx_opsmgmt_py_client/models/OneOfcommon/v1/config/__init__.py
ntnx_opsmgmt_py_client/models/OneOfopsmgmt/__init__.py
ntnx_opsmgmt_py_client/models/OneOfopsmgmt/v4/__init__.py
ntnx_opsmgmt_py_client/models/OneOfopsmgmt/v4/config/CreateReportApiResponsedata.py
ntnx_opsmgmt_py_client/models/OneOfopsmgmt/v4/config/CreateReportConfigApiResponsedata.py
ntnx_opsmgmt_py_client/models/OneOfopsmgmt/v4/config/DeleteReportApiResponsedata.py
ntnx_opsmgmt_py_client/models/OneOfopsmgmt/v4/config/DeleteReportConfigApiResponsedata.py
ntnx_opsmgmt_py_client/models/OneOfopsmgmt/v4/config/GetGlobalReportSettingApiResponsedata.py
ntnx_opsmgmt_py_client/models/OneOfopsmgmt/v4/config/GetReportApiResponsedata.py
ntnx_opsmgmt_py_client/models/OneOfopsmgmt/v4/config/GetReportConfigApiResponsedata.py
ntnx_opsmgmt_py_client/models/OneOfopsmgmt/v4/config/ListReportConfigsApiResponsedata.py
ntnx_opsmgmt_py_client/models/OneOfopsmgmt/v4/config/ListReportsApiResponsedata.py
ntnx_opsmgmt_py_client/models/OneOfopsmgmt/v4/config/NotifyReportApiResponsedata.py
ntnx_opsmgmt_py_client/models/OneOfopsmgmt/v4/config/UpdateGlobalReportSettingsApiResponsedata.py
ntnx_opsmgmt_py_client/models/OneOfopsmgmt/v4/config/UpdateReportConfigApiResponsedata.py
ntnx_opsmgmt_py_client/models/OneOfopsmgmt/v4/config/Widgetwidget_info.py
ntnx_opsmgmt_py_client-4.0.3.dist-info/LICENSE.txt
ntnx_opsmgmt_py_client-4.0.3.dist-info/METADATA
ntnx_opsmgmt_py_client-4.0.3.dist-info/WHEEL
ntnx_opsmgmt_py_client-4.0.3.dist-info/top_level.txt
ntnx_opsmgmt_py_client-4.0.3.dist-info/RECORD
