Metadata-Version: 2.1
Name: ntnx-opsmgmt-py-client
Version: 4.0.3
Summary: Nutanix Cloud Management Platform APIs
Home-page: 
Author-email: sdk@nutanix.com
Keywords: Nutanix,v4,SDK,Nutanix Cloud Management Platform APIs
License-File: LICENSE.txt
Requires-Dist: urllib3 ~=1.26
Requires-Dist: six ~=1.16
Requires-Dist: certifi <=2025.4.26,>=2024.7.4
Requires-Dist: python-dateutil ~=2.8
Requires-Dist: pysocks ~=1.7
